openssl_engine_capi/__init__.py
openssl_engine_capi-1.1.4.dist-info/METADATA
openssl_engine_capi-1.1.4.dist-info/WHEEL
openssl_engine_capi-1.1.4.dist-info/top_level.txt
openssl_engine_capi-1.1.4.dist-info/RECORD
