Metadata-Version: 2.1
Name: openssl-engine-capi
Version: 1.1.4
Summary: Python capi openssl engine support1
Home-page: https://github.com/jose-pr/pypki
Author: Jose A.
Author-email: jose-pr@coqui.dev
License: UNKNOWN
Platform: UNKNOWN
Requires-Dist: openssl-engine
